pretty_id/__init__.py
pretty_id/encoding.py
pretty_id/ext/__init__.py
pretty_id/ext/sqlalchemy.py
pretty_id/type.py
prettyid-0.3.1.dist-info/LICENSE.md
prettyid-0.3.1.dist-info/METADATA
prettyid-0.3.1.dist-info/WHEEL
prettyid-0.3.1.dist-info/RECORD
