Metadata-Version: 2.1
Name: prettyid
Version: 0.3.1
Summary: Pretty cool IDs for your APIs
Home-page: https://codeberg.org/prettyid/python.git
License: Apache-2.0
Author: Alexander Pushkov
Author-email: alexander@notpushk.in
Requires-Python: >=3.12,<4.0
Classifier: Development Status :: 3 - Alpha
Classifier: License :: OSI Approved :: Apache Software License
Classifier: Programming Language :: Python :: 3
Classifier: Programming Language :: Python :: 3.12
Requires-Dist: uuid-utils (>=0.9.0,<0.10.0)
Project-URL: Bug Tracker, https://codeberg.org/prettyid/python/issues
Project-URL: Repository, https://codeberg.org/prettyid/python.git
